flask_extend_headers/__init__.py
flask_extend_headers-1.1.1.dist-info/LICENSE
flask_extend_headers-1.1.1.dist-info/WHEEL
flask_extend_headers-1.1.1.dist-info/METADATA
flask_extend_headers-1.1.1.dist-info/RECORD
